asd/__init__.py
asd/cli.py
asd/core/__init__.py
asd/core/costs.py
asd/core/executor.py
asd/core/git_tools.py
asd/core/graph.py
asd/core/intents.py
asd/core/models.py
asd/core/planner.py
asd/core/visualization.py
asd/ui/__init__.py
asd/ui/display.py
asd/ui/loader.py
asd/ui/prompts.py
asd/ui/themes.py
git_asd-1.1.3.dist-info/licenses/LICENSE
git_asd-1.1.3.dist-info/METADATA
git_asd-1.1.3.dist-info/WHEEL
git_asd-1.1.3.dist-info/entry_points.txt
git_asd-1.1.3.dist-info/top_level.txt
git_asd-1.1.3.dist-info/RECORD
