Metadata-Version: 2.4
Name: git-asd
Version: 1.1.3
Summary: a natural language git assistant for the terminal
Home-page: https://github.com/adikuma/asd
Author: Aditya Kumar
License: MIT
Classifier: License :: OSI Approved :: MIT License
Classifier: Programming Language :: Python :: 3
Classifier: Operating System :: OS Independent
Requires-Python: >=3.9
License-File: LICENSE
Requires-Dist: langchain-core
Requires-Dist: langchain-openai
Requires-Dist: langchain-google-genai
Requires-Dist: langgraph
Requires-Dist: typer[all]
Requires-Dist: rich
Requires-Dist: rich-gradient
Requires-Dist: ruff
Requires-Dist: python-dotenv
Requires-Dist: IPython
Requires-Dist: questionary
Dynamic: author
Dynamic: classifier
Dynamic: description
Dynamic: description-content-type
Dynamic: home-page
Dynamic: license
Dynamic: license-file
Dynamic: requires-dist
Dynamic: requires-python
Dynamic: summary
